jwt/__init__.py
jwt/jwe.py
jwt/jwk.py
jwt/jws.py
jwt/jwt.py
jwt/keystore.py
pyjwt_tspspi-0.0.7.dist-info/licenses/LICENSE.md
pyjwt_tspspi-0.0.7.dist-info/METADATA
pyjwt_tspspi-0.0.7.dist-info/WHEEL
pyjwt_tspspi-0.0.7.dist-info/top_level.txt
pyjwt_tspspi-0.0.7.dist-info/RECORD
