Metadata-Version: 2.4
Name: pyjwt-tspspi
Version: 0.0.7
Summary: JSON Web Token implementation
Home-page: https://github.com/tspspi/pyjwt
Author: Thomas Spielauer
Author-email: pypipackages01@tspi.at
Classifier: Programming Language :: Python :: 3
Classifier: License :: OSI Approved :: BSD License
Classifier: Operating System :: OS Independent
Requires-Python: >=3.9
License-File: LICENSE.md
Requires-Dist: pycryptodomex>=3.21
Dynamic: license-file
